LICENSE
MANIFEST.in
README.rst
setup.cfg
setup.py
skye_users.egg-info/PKG-INFO
skye_users.egg-info/SOURCES.txt
skye_users.egg-info/dependency_links.txt
skye_users.egg-info/top_level.txt
skyeusers/__init__.py
skyeusers/admin.py
skyeusers/apps.py
skyeusers/models.py
skyeusers/serializers.py
skyeusers/tests.py
skyeusers/urls.py
skyeusers/utils.py
skyeusers/views.py
skyeusers/migrations/0001_initial.py
skyeusers/migrations/__init__.py